driver/cli.py
driver/config.yaml
driver/kamvas_driver.py
kamvas_driver-0.1.2.dist-info/LICENSE
kamvas_driver-0.1.2.dist-info/METADATA
kamvas_driver-0.1.2.dist-info/WHEEL
kamvas_driver-0.1.2.dist-info/entry_points.txt
kamvas_driver-0.1.2.dist-info/top_level.txt
kamvas_driver-0.1.2.dist-info/RECORD
