Metadata-Version: 2.1
Name: kamvas-driver
Version: 0.1.2
Summary: A Linux userland driver for Huion Kamvas Pro devices
Home-page: https://github.com/Mantaseus/Huion_Kamvas_linux.git
Author: Mantaseus
License: MIT
Platform: UNKNOWN
Classifier: License :: OSI Approved :: MIT License
Classifier: Operating System :: POSIX :: Linux
Requires-Dist: docopt
Requires-Dist: tabulate
Requires-Dist: pyusb
Requires-Dist: evdev
Requires-Dist: pyyaml
Requires-Dist: psutil
Requires-Dist: elevate
Requires-Dist: pyudev
